pyiextract
