Metadata-Version: 2.1
Name: pyiextract
Version: 0.0.3
Summary: A library for end to end information extraction from raw text.
Home-page: https://github.com/8W9aG/pyiextract
Author: Will Sackfield
Author-email: will.sackfield@gmail.com
License: MIT
Keywords: information extraction nlp
Classifier: License :: OSI Approved :: MIT License
Classifier: Programming Language :: Python :: 3
License-File: LICENSE
